icinga2apic-stubs/__init__.pyi
icinga2apic-stubs/actions.pyi
icinga2apic-stubs/base.pyi
icinga2apic-stubs/client.pyi
icinga2apic-stubs/configfile.pyi
icinga2apic-stubs/events.pyi
icinga2apic-stubs/exceptions.pyi
icinga2apic-stubs/objects.pyi
icinga2apic-stubs/status.pyi
icinga2apic_stubs-0.1.0.dist-info/METADATA
icinga2apic_stubs-0.1.0.dist-info/WHEEL
icinga2apic_stubs-0.1.0.dist-info/RECORD
