Metadata-Version: 2.1
Name: icinga2apic-stubs
Version: 0.1.0
Summary: Type stubs for the icinga2apic package.
Home-page: https://github.com/Josef-Friedrich/icinga2apic-stubs
License: MIT
Author: Josef Friedrich
Author-email: josef@friedrich.rocks
Requires-Python: >=3.8,<4.0
Classifier: License :: OSI Approved :: MIT License
Classifier: Programming Language :: Python :: 3
Classifier: Programming Language :: Python :: 3.8
Classifier: Programming Language :: Python :: 3.9
Classifier: Programming Language :: Python :: 3.10
Classifier: Programming Language :: Python :: 3.11
Classifier: Programming Language :: Python :: 3.12
Project-URL: Repository, https://github.com/Josef-Friedrich/icinga2apic-stubs
